herbarium/__init__.py
herbarium/__main__.py
herbarium/git.py
herbarium/queue_manipulator.py
herbarium/cli/__init__.py
herbarium/cli/config.py
herbarium/cli/interface_elements.py
herbarium/cli/location.py
herbarium/cli/manipulation.py
herbarium/cli/navigation.py
herbarium/cli/subprocess_utils.py
herbarium/issues/__init__.py
herbarium/issues/controller.py
herbarium/issues/issue_stringifyer.py
herbarium/issues/model.py
herbarium/issues/stringifyer.py
herbarium/issues/test_issue_service.py
herbarium/issues/test_model.py
herbarium/issues/test_stringifyer.py
herbarium/issues/test_title_parser.py
herbarium/issues/title_parser.py
herbarium/issues/view.py
herbarium/queue/__init__.py
herbarium/queue/manipulator.py
herbarium/queue/navigator.py
herbarium-0.32.1.dist-info/LICENSE
herbarium-0.32.1.dist-info/METADATA
herbarium-0.32.1.dist-info/WHEEL
herbarium-0.32.1.dist-info/entry_points.txt
herbarium-0.32.1.dist-info/top_level.txt
herbarium-0.32.1.dist-info/RECORD
