Metadata-Version: 2.1
Name: herbarium
Version: 0.32.1
Summary: Herbarium
Author-email: Martin Bernstorff <martinbernstorff@gmail.com>
License: MIT License
Project-URL: homepage, https://github.com/MartinBernstorff/herbarium
Project-URL: repository, https://github.com/MartinBernstorff/herbarium
Project-URL: documentation, https://MartinBernstorff.github.io/herbarium/
Classifier: Programming Language :: Python :: 3.9
Classifier: Programming Language :: Python :: 3.10
Classifier: Programming Language :: Python :: 3.11
Classifier: Programming Language :: Python :: 3.12
Requires-Python: >=3.9
License-File: LICENSE
Requires-Dist: typer
Requires-Dist: questionary
Provides-Extra: dev
Requires-Dist: cruft ==2.15.0 ; extra == 'dev'
Requires-Dist: pyright ==1.1.346 ; extra == 'dev'
Requires-Dist: pytest ==7.4.3 ; extra == 'dev'
Requires-Dist: pytest-cov ==4.1.0 ; extra == 'dev'
Requires-Dist: pytest-xdist ==3.5.0 ; extra == 'dev'
Requires-Dist: pytest-sugar ==0.9.7 ; extra == 'dev'
Requires-Dist: diff-cover ==8.0.1 ; extra == 'dev'
Requires-Dist: ruff ==0.1.13 ; extra == 'dev'
